LICENSE.txt
README.md
setup.cfg
setup.py
base/__init__.py
base/dtk1.py
base/numk.py
data/__init__.py
data/ts.py
handle/__init__.py
handle/quant.py
kv/__init__.py
kv/pdk.py
poldark_qt.egg-info/PKG-INFO
poldark_qt.egg-info/SOURCES.txt
poldark_qt.egg-info/dependency_links.txt
poldark_qt.egg-info/requires.txt
poldark_qt.egg-info/top_level.txt
test/__init__.py
test/aho.py